{
  "agent": "developer",
  "mode": "edit",
  "timestamp": "2026-02-18-150215",
  "blockName": "archive",
  "blockPath": "blocks/Archive",
  "change": "Replace before:bg-charcoal with before:bg-dark-pattern in dark mode classes",
  "filesModified": [
    "blocks/Archive/Archive.tsx",
    "blocks/Archive/Archive.php"
  ],
  "occurrences": {
    "Archive.tsx": 1,
    "Archive.php": 1
  },
  "validation": {
    "passed": true,
    "errors": 0,
    "warnings": 9,
    "warningsArePreExisting": true
  },
  "status": "complete"
}
